ovos_solver_llamacpp/__init__.py
ovos_solver_llamacpp/personas.py
ovos_solver_llamacpp/version.py
ovos_solver_llamacpp_plugin-0.0.0a1.dist-info/LICENSE
ovos_solver_llamacpp_plugin-0.0.0a1.dist-info/METADATA
ovos_solver_llamacpp_plugin-0.0.0a1.dist-info/WHEEL
ovos_solver_llamacpp_plugin-0.0.0a1.dist-info/entry_points.txt
ovos_solver_llamacpp_plugin-0.0.0a1.dist-info/top_level.txt
ovos_solver_llamacpp_plugin-0.0.0a1.dist-info/zip-safe
ovos_solver_llamacpp_plugin-0.0.0a1.dist-info/RECORD
