Metadata-Version: 2.1
Name: ovos-solver-llamacpp-plugin
Version: 0.0.0a1
Summary: A question solver plugin for ovos
Home-page: https://github.com/OpenVoiceOS/ovos-solver-plugin-llamacpp
Author: jarbasai
Author-email: jarbasai@mailfence.com
License: MIT
Keywords: ovos plugin utterance fallback query
Platform: UNKNOWN
Requires-Dist: llamacpp
Requires-Dist: neon-solvers
